README.md
setup.cfg
setup.py
standup_and_prosper_sdk/VERSION
standup_and_prosper_sdk/__init__.py
standup_and_prosper_sdk/api_client.py
standup_and_prosper_sdk/rest.py
standup_and_prosper_sdk.egg-info/PKG-INFO
standup_and_prosper_sdk.egg-info/SOURCES.txt
standup_and_prosper_sdk.egg-info/dependency_links.txt
standup_and_prosper_sdk.egg-info/requires.txt
standup_and_prosper_sdk.egg-info/top_level.txt
standup_and_prosper_sdk/api/__init__.py
standup_and_prosper_sdk/api/standups_api.py
standup_and_prosper_sdk/models/__init__.py
standup_and_prosper_sdk/models/question.py
standup_and_prosper_sdk/models/response.py
standup_and_prosper_sdk/models/thread.py
standup_and_prosper_sdk/models/thread_collection.py
standup_and_prosper_sdk/models/user_response.py