Metadata-Version: 2.1
Name: standup-and-prosper-sdk
Version: 1.0.13
Summary: The Standup & Prosper SDK for interacting with standups programmatically.
Home-page: https://github.com/Teaminator/standup-and-prosper-sdk.py.git
Author: Rhosys Developers
Author-email: developers@teaminator.io
License: Apache-2.0
Keywords: Standups,Stand ups,Dailies,Standup & Prosper,Teaminator
Platform: UNKNOWN
